django_simpleui_captcha-0.1.4.dist-info/licenses/LICENSE
simpleui_captcha/__init__.py
simpleui_captcha/admin.py
simpleui_captcha/apps.py
simpleui_captcha/forms.py
simpleui_captcha/settings.py
simpleui_captcha/urls.py
simpleui_captcha/views.py
simpleui_captcha/migrations/__init__.py
simpleui_captcha/templates/admin/login.html
django_simpleui_captcha-0.1.4.dist-info/METADATA
django_simpleui_captcha-0.1.4.dist-info/WHEEL
django_simpleui_captcha-0.1.4.dist-info/top_level.txt
django_simpleui_captcha-0.1.4.dist-info/RECORD
